ctimeit/__init__.py
ctimeit/ctimeit.py
ctimeit-1.0.0.dist-info/LICENSE
ctimeit-1.0.0.dist-info/METADATA
ctimeit-1.0.0.dist-info/WHEEL
ctimeit-1.0.0.dist-info/top_level.txt
ctimeit-1.0.0.dist-info/RECORD
